start_django_app/__init__.py
start_django_app/cli.py
start_django_app/start_django_app.py
start_django_app-0.2.dist-info/LICENSE
start_django_app-0.2.dist-info/METADATA
start_django_app-0.2.dist-info/WHEEL
start_django_app-0.2.dist-info/entry_points.txt
start_django_app-0.2.dist-info/top_level.txt
start_django_app-0.2.dist-info/RECORD
